setup.cfg
setup.py
bin/git-lab
git_gitlab.egg-info/PKG-INFO
git_gitlab.egg-info/SOURCES.txt
git_gitlab.egg-info/dependency_links.txt
git_gitlab.egg-info/not-zip-safe
git_gitlab.egg-info/requires.txt
git_gitlab.egg-info/top_level.txt
gitgitlab/__init__.py
gitgitlab/bin/__init__.py
gitgitlab/test/__init__.py
gitgitlab/test/gitgitlab_test.py