Metadata-Version: 1.1
Name: git-gitlab
Version: 0.6.0
Summary: Git extension commandline for GitLab API v3
Home-page: https://gitlab.com/bor-sh/git-gitlab
Author: b-sh
Author-email: b-sh@gmx.net
License: MIT
Platform: any
Classifier: Development Status :: 3 - Alpha
Classifier: Environment :: Console
Classifier: Intended Audience :: Developers
Classifier: License :: OSI Approved :: MIT License
Classifier: Operating System :: OS Independent
Classifier: Operating System :: POSIX
Classifier: Programming Language :: Python
Classifier: Topic :: Software Development :: Version Control
